{
  "2": {},
  "global": {
    "Green": {
      "G-800": {
        "value": "#103d25",
        "type": "color"
      },
      "G-700": {
        "value": "#1b653d",
        "type": "color"
      },
      "G-600": {
        "value": "#258d55",
        "type": "color"
      },
      "G-500": {
        "value": "#30b66e",
        "type": "color"
      },
      "G-400": {
        "value": "#49cf87",
        "type": "color"
      },
      "G-300": {
        "value": "#72daa2",
        "type": "color"
      },
      "G-200": {
        "value": "#9ae4bc",
        "type": "color"
      }
    },
    "Yellow": {
      "Y-500": {
        "value": "#ffc14a",
        "type": "color"
      },
      "Y-400": {
        "value": "#ffd27a",
        "type": "color"
      },
      "Y-300": {
        "value": "#ffe3ad",
        "type": "color"
      },
      "Y-200": {
        "value": "#fff5e0",
        "type": "color"
      },
      "Y-600": {
        "value": "#ffaf14",
        "type": "color"
      },
      "Y-700": {
        "value": "#e09400",
        "type": "color"
      },
      "Y-800": {
        "value": "#ad7200",
        "type": "color"
      }
    },
    "Greenish Gray": {
      "G-800": {
        "value": "#1a211d",
        "type": "color"
      },
      "G-700": {
        "value": "#323e38",
        "type": "color"
      },
      "G-600": {
        "value": "#59625c",
        "type": "color"
      },
      "G-500": {
        "value": "#8d948f",
        "type": "color"
      },
      "G-400": {
        "value": "#aeb4b0",
        "type": "color"
      },
      "G-300": {
        "value": "#dce0de",
        "type": "color"
      },
      "G-200": {
        "value": "#f6f8f7",
        "type": "color"
      },
      "G-100": {
        "value": "#fbfbfb",
        "type": "color"
      }
    },
    "Light Grenn": {
      "G-500": {
        "value": "#64c74c",
        "type": "color"
      },
      "G-600": {
        "value": "#4cab35",
        "type": "color"
      },
      "G-700": {
        "value": "#3b8429",
        "type": "color"
      },
      "G-800": {
        "value": "#2a5d1d",
        "type": "color"
      },
      "G-400": {
        "value": "#a8e09a",
        "type": "color"
      },
      "G-300": {
        "value": "#c9ecc1",
        "type": "color"
      },
      "G-200": {
        "value": "#ebf8e8",
        "type": "color"
      }
    },
    "Blue": {
      "B-500": {
        "value": "#1c84ff",
        "type": "color"
      },
      "B-400": {
        "value": "#4c9eff",
        "type": "color"
      },
      "B-300": {
        "value": "#80baff",
        "type": "color"
      },
      "B-200": {
        "value": "#b3d6ff",
        "type": "color"
      },
      "B-100": {
        "value": "#e5f1ff",
        "type": "color"
      }
    },
    "Orange": {
      "O-500": {
        "value": "#f09847",
        "type": "color"
      },
      "O-400": {
        "value": "#f4b376",
        "type": "color"
      },
      "O-300": {
        "value": "#fce7d5",
        "type": "color"
      },
      "O-200": {
        "value": "#fef7f1",
        "type": "color"
      },
      "O-600": {
        "value": "#ec7d17",
        "type": "color"
      },
      "O-700": {
        "value": "#c16510",
        "type": "color"
      },
      "O-800": {
        "value": "#924c0c",
        "type": "color"
      }
    },
    "Line": {
      "G-100": {
        "value": "#f1f4f4",
        "type": "color"
      },
      "G-200": {
        "value": "#eceded",
        "type": "color"
      },
      "G-300": {
        "value": "#e6e6e6",
        "type": "color"
      },
      "G-400": {
        "value": "#dfdfdf",
        "type": "color"
      }
    },
    "Red": {
      "R-500": {
        "value": "#fa4343",
        "type": "color"
      },
      "R-400": {
        "value": "#d26a6a",
        "type": "color"
      },
      "R-300": {
        "value": "#de9191",
        "type": "color"
      },
      "R-200": {
        "value": "#eab8b8",
        "type": "color"
      },
      "R-100": {
        "value": "#f6e0e0",
        "type": "color"
      }
    },
    "Bottom Sheet": {
      "value": {
        "color": "#0000001a",
        "type": "dropShadow",
        "x": 0,
        "y": -3,
        "blur": 18,
        "spread": 0
      },
      "type": "boxShadow"
    },
    "List": {
      "value": {
        "color": "#0000001a",
        "type": "dropShadow",
        "x": 0,
        "y": 4,
        "blur": 8,
        "spread": 0
      },
      "type": "boxShadow"
    },
    "Shadow": {
      "Pin Location": {
        "value": {
          "color": "#0000002e",
          "type": "dropShadow",
          "x": 0,
          "y": 4,
          "blur": 8,
          "spread": 0
        },
        "type": "boxShadow"
      },
      "Float Button": {
        "value": {
          "color": "#00000026",
          "type": "dropShadow",
          "x": 4,
          "y": 10,
          "blur": 20,
          "spread": 0
        },
        "type": "boxShadow"
      }
    },
    "fontFamilies": {
      "pretendard": {
        "value": "Pretendard",
        "type": "fontFamilies"
      }
    },
    "lineHeights": {
      "0": {
        "value": "18",
        "type": "lineHeights"
      },
      "1": {
        "value": "28",
        "type": "lineHeights"
      },
      "2": {
        "value": "25",
        "type": "lineHeights"
      },
      "3": {
        "value": "24",
        "type": "lineHeights"
      },
      "4": {
        "value": "22",
        "type": "lineHeights"
      },
      "5": {
        "value": "20",
        "type": "lineHeights"
      },
      "6": {
        "value": "34",
        "type": "lineHeights"
      }
    },
    "fontWeights": {
      "pretendard-0": {
        "value": "Medium",
        "type": "fontWeights"
      },
      "pretendard-1": {
        "value": "SemiBold",
        "type": "fontWeights"
      },
      "pretendard-2": {
        "value": "Regular",
        "type": "fontWeights"
      },
      "pretendard-3": {
        "value": "Bold",
        "type": "fontWeights"
      }
    },
    "fontSize": {
      "0": {
        "value": "11",
        "type": "fontSizes"
      },
      "1": {
        "value": "12",
        "type": "fontSizes"
      },
      "2": {
        "value": "14",
        "type": "fontSizes"
      },
      "3": {
        "value": "15",
        "type": "fontSizes"
      },
      "4": {
        "value": "16",
        "type": "fontSizes"
      },
      "5": {
        "value": "18",
        "type": "fontSizes"
      },
      "6": {
        "value": "20",
        "type": "fontSizes"
      },
      "7": {
        "value": "24",
        "type": "fontSizes"
      }
    },
    "letterSpacing": {
      "0": {
        "value": "0",
        "type": "letterSpacing"
      },
      "1": {
        "value": "0%",
        "type": "letterSpacing"
      }
    },
    "paragraphSpacing": {
      "0": {
        "value": "0",
        "type": "paragraphSpacing"
      },
      "1": {
        "value": "18",
        "type": "paragraphSpacing"
      }
    },
    "Caption": {
      "value": {
        "fontFamily": "{fontFamilies.pretendard}",
        "fontWeight": "{fontWeights.pretendard-0}",
        "lineHeight": "{lineHeights.0}",
        "fontSize": "{fontSize.1}",
        "letterSpacing": "{letterSpacing.0}",
        "paragraphSpacing": "{paragraphSpacing.0}",
        "paragraphIndent": "{paragraphIndent.0}",
        "textCase": "{textCase.none}",
        "textDecoration": "{textDecoration.none}"
      },
      "type": "typography"
    },
    "Title": {
      "Title-1": {
        "value": {
          "fontFamily": "{fontFamilies.pretendard}",
          "fontWeight": "{fontWeights.pretendard-1}",
          "lineHeight": "{lineHeights.1}",
          "fontSize": "{fontSize.6}",
          "letterSpacing": "{letterSpacing.0}",
          "paragraphSpacing": "{paragraphSpacing.0}",
          "paragraphIndent": "{paragraphIndent.0}",
          "textCase": "{textCase.none}",
          "textDecoration": "{textDecoration.none}"
        },
        "type": "typography"
      },
      "Title-2": {
        "value": {
          "fontFamily": "{fontFamilies.pretendard}",
          "fontWeight": "{fontWeights.pretendard-1}",
          "lineHeight": "{lineHeights.2}",
          "fontSize": "{fontSize.5}",
          "letterSpacing": "{letterSpacing.0}",
          "paragraphSpacing": "{paragraphSpacing.0}",
          "paragraphIndent": "{paragraphIndent.0}",
          "textCase": "{textCase.none}",
          "textDecoration": "{textDecoration.none}"
        },
        "type": "typography"
      },
      "Title-3": {
        "value": {
          "fontFamily": "{fontFamilies.pretendard}",
          "fontWeight": "{fontWeights.pretendard-1}",
          "lineHeight": "{lineHeights.3}",
          "fontSize": "{fontSize.4}",
          "letterSpacing": "{letterSpacing.0}",
          "paragraphSpacing": "{paragraphSpacing.0}",
          "paragraphIndent": "{paragraphIndent.0}",
          "textCase": "{textCase.none}",
          "textDecoration": "{textDecoration.none}"
        },
        "type": "typography"
      },
      "Title-4": {
        "value": {
          "fontFamily": "{fontFamilies.pretendard}",
          "fontWeight": "{fontWeights.pretendard-1}",
          "lineHeight": "{lineHeights.4}",
          "fontSize": "{fontSize.3}",
          "letterSpacing": "{letterSpacing.1}",
          "paragraphSpacing": "{paragraphSpacing.0}",
          "paragraphIndent": "{paragraphIndent.0}",
          "textCase": "{textCase.none}",
          "textDecoration": "{textDecoration.none}"
        },
        "type": "typography"
      },
      "Title-5": {
        "value": {
          "fontFamily": "{fontFamilies.pretendard}",
          "fontWeight": "{fontWeights.pretendard-1}",
          "lineHeight": "{lineHeights.5}",
          "fontSize": "{fontSize.2}",
          "letterSpacing": "{letterSpacing.0}",
          "paragraphSpacing": "{paragraphSpacing.0}",
          "paragraphIndent": "{paragraphIndent.0}",
          "textCase": "{textCase.none}",
          "textDecoration": "{textDecoration.none}"
        },
        "type": "typography"
      },
      "Title-6": {
        "value": {
          "fontFamily": "{fontFamilies.pretendard}",
          "fontWeight": "{fontWeights.pretendard-1}",
          "lineHeight": "{lineHeights.5}",
          "fontSize": "{fontSize.0}",
          "letterSpacing": "{letterSpacing.0}",
          "paragraphSpacing": "{paragraphSpacing.1}",
          "paragraphIndent": "{paragraphIndent.0}",
          "textCase": "{textCase.none}",
          "textDecoration": "{textDecoration.none}"
        },
        "type": "typography"
      }
    },
    "Body": {
      "Body-2": {
        "value": {
          "fontFamily": "{fontFamilies.pretendard}",
          "fontWeight": "{fontWeights.pretendard-2}",
          "lineHeight": "{lineHeights.3}",
          "fontSize": "{fontSize.4}",
          "letterSpacing": "{letterSpacing.0}",
          "paragraphSpacing": "{paragraphSpacing.0}",
          "paragraphIndent": "{paragraphIndent.0}",
          "textCase": "{textCase.none}",
          "textDecoration": "{textDecoration.none}"
        },
        "type": "typography"
      },
      "Body-1": {
        "value": {
          "fontFamily": "{fontFamilies.pretendard}",
          "fontWeight": "{fontWeights.pretendard-0}",
          "lineHeight": "{lineHeights.1}",
          "fontSize": "{fontSize.5}",
          "letterSpacing": "{letterSpacing.0}",
          "paragraphSpacing": "{paragraphSpacing.0}",
          "paragraphIndent": "{paragraphIndent.0}",
          "textCase": "{textCase.none}",
          "textDecoration": "{textDecoration.none}"
        },
        "type": "typography"
      },
      "Body-3": {
        "value": {
          "fontFamily": "{fontFamilies.pretendard}",
          "fontWeight": "{fontWeights.pretendard-0}",
          "lineHeight": "{lineHeights.3}",
          "fontSize": "{fontSize.2}",
          "letterSpacing": "{letterSpacing.0}",
          "paragraphSpacing": "{paragraphSpacing.0}",
          "paragraphIndent": "{paragraphIndent.0}",
          "textCase": "{textCase.none}",
          "textDecoration": "{textDecoration.none}"
        },
        "type": "typography"
      },
      "Body-4": {
        "value": {
          "fontFamily": "{fontFamilies.pretendard}",
          "fontWeight": "{fontWeights.pretendard-0}",
          "lineHeight": "{lineHeights.0}",
          "fontSize": "{fontSize.1}",
          "letterSpacing": "{letterSpacing.0}",
          "paragraphSpacing": "{paragraphSpacing.0}",
          "paragraphIndent": "{paragraphIndent.0}",
          "textCase": "{textCase.none}",
          "textDecoration": "{textDecoration.none}"
        },
        "type": "typography"
      }
    },
    "Heading": {
      "Heading-4": {
        "value": {
          "fontFamily": "{fontFamilies.pretendard}",
          "fontWeight": "{fontWeights.pretendard-3}",
          "lineHeight": "{lineHeights.3}",
          "fontSize": "{fontSize.4}",
          "letterSpacing": "{letterSpacing.0}",
          "paragraphSpacing": "{paragraphSpacing.0}",
          "paragraphIndent": "{paragraphIndent.0}",
          "textCase": "{textCase.none}",
          "textDecoration": "{textDecoration.none}"
        },
        "type": "typography"
      },
      "Heading-2": {
        "value": {
          "fontFamily": "{fontFamilies.pretendard}",
          "fontWeight": "{fontWeights.pretendard-3}",
          "lineHeight": "{lineHeights.1}",
          "fontSize": "{fontSize.6}",
          "letterSpacing": "{letterSpacing.0}",
          "paragraphSpacing": "{paragraphSpacing.0}",
          "paragraphIndent": "{paragraphIndent.0}",
          "textCase": "{textCase.none}",
          "textDecoration": "{textDecoration.none}"
        },
        "type": "typography"
      },
      "Heading-1": {
        "value": {
          "fontFamily": "{fontFamilies.pretendard}",
          "fontWeight": "{fontWeights.pretendard-1}",
          "lineHeight": "{lineHeights.6}",
          "fontSize": "{fontSize.7}",
          "letterSpacing": "{letterSpacing.0}",
          "paragraphSpacing": "{paragraphSpacing.0}",
          "paragraphIndent": "{paragraphIndent.0}",
          "textCase": "{textCase.none}",
          "textDecoration": "{textDecoration.none}"
        },
        "type": "typography"
      },
      "Heading-3": {
        "value": {
          "fontFamily": "{fontFamilies.pretendard}",
          "fontWeight": "{fontWeights.pretendard-3}",
          "lineHeight": "{lineHeights.2}",
          "fontSize": "{fontSize.5}",
          "letterSpacing": "{letterSpacing.0}",
          "paragraphSpacing": "{paragraphSpacing.0}",
          "paragraphIndent": "{paragraphIndent.0}",
          "textCase": "{textCase.none}",
          "textDecoration": "{textDecoration.none}"
        },
        "type": "typography"
      }
    },
    "textCase": {
      "none": {
        "value": "none",
        "type": "textCase"
      }
    },
    "textDecoration": {
      "none": {
        "value": "none",
        "type": "textDecoration"
      }
    },
    "paragraphIndent": {
      "0": {
        "value": "0px",
        "type": "dimension"
      }
    }
  },
  "$themes": [],
  "$metadata": {
    "tokenSetOrder": [
      "2",
      "global"
    ]
  }
}